sunlite/__init__.py
sunlite/db.py
sunlite-0.2.0.dist-info/METADATA
sunlite-0.2.0.dist-info/RECORD
sunlite-0.2.0.dist-info/WHEEL
sunlite-0.2.0.dist-info/top_level.txt
