Metadata-Version: 2.1
Name: sunlite
Version: 0.2.0
Summary: A simple database system
Home-page: https://sunx2.github.io/sunlite/
Author: Sun
Author-email: sun600@outlook.com
License: UNKNOWN
Platform: UNKNOWN
Classifier: Programming Language :: Python :: 3
Classifier: License :: OSI Approved :: MIT License
Classifier: Operating System :: OS Independent
